{
 "B94.1": {
  "diagnose": "Folgezustände der Virusenzephalitis",
  "gruppen": [
   "EN1",
   "RE1",
   "RE2",
   "SC",
   "SF",
   "SO3",
   "SP1",
   "SP3",
   "SP4",
   "SP5",
   "ST1",
   "ZN"
  ],
  "hinweis": "längstens 1 Jahr nach Akutereignis"
 },
 "C70.0": {
  "diagnose": "Hirnhäute",
  "gruppen": [
   "SO1",
   "SO3",
   "SP2",
   "SP3",
   "SP5"
  ],
  "hinweis": "nach Akutereignis"
 },
 "C70.1": {
  "diagnose": "Rückenmarkhäute",
  "gruppen": [
   "RE1",
   "RE2",
   "SP6"
  ],
  "hinweis": ""
 },
 "C70.9": {
  "diagnose": "Meningen, nicht näher bezeichnet",
  "gruppen": [
   "SF"
  ],
  "hinweis": ""
 },
 "C71.0": {
  "diagnose": "Zerebrum, ausgenommen Hirnlappen und Ventrikel",
  "gruppen": [],
  "hinweis": ""
 },
 "C71.1": {
  "diagnose": "Frontallappen",
  "gruppen": [],
  "hinweis": ""
 },
 "C71.2": {
  "diagnose": "Temporallappen",
  "gruppen": [],
  "hinweis": ""
 },
 "C71.3": {
  "diagnose": "Parietallappen",
  "gruppen": [],
  "hinweis": ""
 },
 "C71.4": {
  "diagnose": "Okzipitallappen",
  "gruppen": [],
  "hinweis": ""
 },
 "C71.5": {
  "diagnose": "Hirnventrikel",
  "gruppen": [],
  "hinweis": ""
 },
 "C71.6": {
  "diagnose": "Zerebellum",
  "gruppen": [],
  "hinweis": ""
 },
 "C71.7": {
  "diagnose": "Hirnstamm",
  "gruppen": [],
  "hinweis": ""
 },
 "C71.8": {
  "diagnose": "Gehirn, mehrere Teilbereiche überlappend",
  "gruppen": [],
  "hinweis": ""
 },
 "C71.9": {
  "diagnose": "Gehirn, nicht näher bezeichnet",
  "gruppen": [],
  "hinweis": ""
 },
 "C72.0": {
  "diagnose": "Rückenmark",
  "gruppen": [],
  "hinweis": ""
 },
 "C72.1": {
  "diagnose": "Cauda equina",
  "gruppen": [],
  "hinweis": ""
 },
 "C72.2": {
  "diagnose": "Nn. olfactorii [I. Hirnnerv]",
  "gruppen": [],
  "hinweis": ""
 },
 "C72.3": {
  "diagnose": "N. opticus [II. Hirnnerv]",
  "gruppen": [],
  "hinweis": ""
 },
 "C72.4": {
  "diagnose": "N. vestibulocochlearis [VIII. Hirnnerv]",
  "gruppen": [],
  "hinweis": ""
 },
 "C72.5": {
  "diagnose": "Sonstige und nicht näher bezeichnete Hirnnerven",
  "gruppen": [],
  "hinweis": ""
 },
 "C72.8": {
  "diagnose": "Gehirn und andere Teile des Zentral- nervensystems, mehrere Teilbereiche überlappend",
  "gruppen": [],
  "hinweis": ""
 },
 "C72.9": {
  "diagnose": "Zentralnervensystem, nicht näher bezeichnet",
  "gruppen": [],
  "hinweis": ""
 },
 "G10": {
  "diagnose": "Chorea Huntington",
  "gruppen": [
   "EN1",
   "SC",
   "SP5",
   "SP6",
   "ZN"
  ],
  "hinweis": ""
 },
 "G11.0": {
  "diagnose": "Angeborene nichtprogressive Ataxie",
  "gruppen": [
   "EN1",
   "SC",
   "ZN"
  ],
  "hinweis": ""
 },
 "G11.1": {
  "diagnose": "Früh beginnende zerebellare Ataxie",
  "gruppen": [
   "EN1",
   "SC",
   "ZN"
  ],
  "hinweis": ""
 },
 "G11.2": {
  "diagnose": "Spät beginnende zerebellare Ataxie",
  "gruppen": [
   "EN1",
   "SC",
   "ZN"
  ],
  "hinweis": ""
 },
 "G11.3": {
  "diagnose": "Zerebellare Ataxie mit defektem DNA-Re- paratursystem",
  "gruppen": [
   "EN1",
   "SC",
   "ZN"
  ],
  "hinweis": ""
 },
 "G11.4": {
  "diagnose": "Hereditäre spastische Paraplegie",
  "gruppen": [
   "EN1",
   "SC",
   "ZN"
  ],
  "hinweis": ""
 },
 "G11.8": {
  "diagnose": "Sonstige hereditäre Ataxien",
  "gruppen": [
   "EN1",
   "SC",
   "ZN"
  ],
  "hinweis": ""
 },
 "G11.9": {
  "diagnose": "Hereditäre Ataxie, nicht näher bezeichnet",
  "gruppen": [
   "EN1",
   "SC",
   "ZN"
  ],
  "hinweis": ""
 },
 "G12.0": {
  "diagnose": "Infantile spinale Muskelatrophie, Typ I [Typ Werdnig-Hoffmann]",
  "gruppen": [
   "AT",
   "EN2",
   "SB3",
   "SC",
   "SP6",
   "ZN"
  ],
  "hinweis": ""
 },
 "G12.1": {
  "diagnose": "Sonstige vererbte spinale Muskelatrophie",
  "gruppen": [
   "AT",
   "EN2",
   "SB3",
   "SC",
   "SP6",
   "ZN"
  ],
  "hinweis": ""
 },
 "G12.2": {
  "diagnose": "Motoneuron-Krankheit",
  "gruppen": [
   "AT",
   "EN2",
   "SB3",
   "SC",
   "SP6",
   "ZN"
  ],
  "hinweis": ""
 },
 "G12.8": {
  "diagnose": "Sonstige spinale Muskelatrophien und verwandte Syndrome",
  "gruppen": [
   "AT",
   "EN2",
   "SB3",
   "SC",
   "SP6",
   "ZN"
  ],
  "hinweis": ""
 },
 "G12.9": {
  "diagnose": "Spinale Muskelatrophie, nicht näher bezeichnet",
  "gruppen": [
   "AT",
   "EN2",
   "SB3",
   "SC",
   "SP6",
   "ZN"
  ],
  "hinweis": ""
 },
 "G14": {
  "diagnose": "Postpoliosyndrom",
  "gruppen": [
   "AT",
   "EN1",
   "EN2",
   "EN3",
   "PN",
   "SC",
   "SP6",
   "ZN"
  ],
  "hinweis": ""
 },
 "G21.3": {
  "diagnose": "Postenzephalitisches Parkinson-Syndrom",
  "gruppen": [
   "EN1",
   "SC",
   "SP6",
   "ZN"
  ],
  "hinweis": ""
 },
 "G21.4": {
  "diagnose": "Vaskuläres Parkinson-Syndrom",
  "gruppen": [
   "EN1",
   "SC",
   "SP6",
   "ZN"
  ],
  "hinweis": ""
 },
 "G21.8": {
  "diagnose": "Sonstiges sekundäres Parkinson-Syndrom",
  "gruppen": [
   "EN1",
   "SC",
   "SP6",
   "ZN"
  ],
  "hinweis": ""
 },
 "G24.3": {
  "diagnose": "Torticollis spasticus",
  "gruppen": [
   "ZN"
  ],
  "hinweis": "nur bei gleichzeitiger leitliniengerechter medikamentöser Therapie"
 },
 "G35.0": {
  "diagnose": "Erstmanifestation einer multiplen Skle- rose",
  "gruppen": [
   "EN1",
   "EN2",
   "SC",
   "SP5",
   "SP6",
   "ST1",
   "ZN"
  ],
  "hinweis": ""
 },
 "G35.9": {
  "diagnose": "Multiple Sklerose, nicht näher bezeichnet",
  "gruppen": [],
  "hinweis": ""
 },
 "G36.0": {
  "diagnose": "Neuromyelitis optica [Devic-Krankheit]",
  "gruppen": [],
  "hinweis": ""
 },
 "G36.1": {
  "diagnose": "Akute und subakute hämorrhagische Leukoenzephalitis [Hurst]",
  "gruppen": [],
  "hinweis": ""
 },
 "G36.8": {
  "diagnose": "Sonstige näher bezeichnete akute dis- seminierte Demyelinisation",
  "gruppen": [],
  "hinweis": ""
 },
 "G36.9": {
  "diagnose": "Akute disseminierte Demyelinisation, nicht näher bezeichnet",
  "gruppen": [],
  "hinweis": ""
 },
 "G37.0": {
  "diagnose": "Diffuse Hirnsklerose",
  "gruppen": [
   "EN1",
   "EN2",
   "SC",
   "SP5",
   "SP6",
   "ST1",
   "ZN"
  ],
  "hinweis": ""
 },
 "G37.1": {
  "diagnose": "Zentrale Demyelinisation des Corpus callosum",
  "gruppen": [
   "EN1",
   "EN2",
   "SC",
   "SP5",
   "SP6",
   "ST1",
   "ZN"
  ],
  "hinweis": ""
 },
 "G37.2": {
  "diagnose": "Zentrale pontine Myelinolyse",
  "gruppen": [
   "EN1",
   "EN2",
   "SC",
   "SP5",
   "SP6",
   "ST1",
   "ZN"
  ],
  "hinweis": ""
 },
 "G37.3": {
  "diagnose": "Myelitis transversa acuta bei demyelini- sierender Krankheit des Zentralnerven- systems",
  "gruppen": [
   "EN1",
   "EN2",
   "SC",
   "SP5",
   "SP6",
   "ST1",
   "ZN"
  ],
  "hinweis": ""
 },
 "G37.4": {
  "diagnose": "Subakute nekrotisierende Myelitis [Foix- Alajouanine-Syndrom]",
  "gruppen": [
   "EN1",
   "EN2",
   "SC",
   "SP5",
   "SP6",
   "ST1",
   "ZN"
  ],
  "hinweis": ""
 },
 "G37.5": {
  "diagnose": "Konzentrische Sklerose [Baló-Krankheit]",
  "gruppen": [
   "EN1",
   "EN2",
   "SC",
   "SP5",
   "SP6",
   "ST1",
   "ZN"
  ],
  "hinweis": ""
 },
 "G37.8": {
  "diagnose": "Sonstige näher bezeichnete demyelini- sierende Krankheiten des Zentralnerven- systems",
  "gruppen": [
   "EN1",
   "EN2",
   "SC",
   "SP5",
   "SP6",
   "ST1",
   "ZN"
  ],
  "hinweis": ""
 },
 "G37.9": {
  "diagnose": "Demyelinisierende Krankheit des Zentral- nervensystems, nicht näher bezeichnet",
  "gruppen": [
   "EN1",
   "EN2",
   "SC",
   "SP5",
   "SP6",
   "ST1",
   "ZN"
  ],
  "hinweis": ""
 },
 "G60.0": {
  "diagnose": "Hereditäre sensomotorische Neuropathie",
  "gruppen": [
   "EN3",
   "EX",
   "PN",
   "SB2",
   "SP3",
   "WS"
  ],
  "hinweis": ""
 },
 "G60.8": {
  "diagnose": "Sonstige hereditäre und idiopathische Neuropathien",
  "gruppen": [
   "CS",
   "EN3",
   "EX",
   "PN",
   "SB1",
   "SB2",
   "SO4"
  ],
  "hinweis": ""
 },
 "G61.0": {
  "diagnose": "Guillain-Barré-Syndrom",
  "gruppen": [
   "EN3",
   "PN"
  ],
  "hinweis": ""
 },
 "G61.8": {
  "diagnose": "Sonstige Polyneuritiden",
  "gruppen": [
   "EN3",
   "PN"
  ],
  "hinweis": "nur chronisch inflammatorische demyelinisierende Polyradikuloneuro- pathie (CIDP)"
 },
 "G70.0": {
  "diagnose": "Myasthenia gravis",
  "gruppen": [
   "EN1",
   "SB3",
   "SC",
   "SP6",
   "ZN"
  ],
  "hinweis": ""
 },
 "G70.2": {
  "diagnose": "Angeborene oder entwicklungsbedingte Myasthenie",
  "gruppen": [
   "AT",
   "EN3",
   "PN",
   "SB3",
   "SC",
   "SP6"
  ],
  "hinweis": ""
 },
 "G71.1": {
  "diagnose": "Myotone Syndrome",
  "gruppen": [
   "AT",
   "EN3",
   "PN",
   "SB3",
   "SC",
   "SP6"
  ],
  "hinweis": ""
 },
 "G71.2": {
  "diagnose": "Angeborene Myopathien",
  "gruppen": [
   "AT",
   "EN3",
   "EX",
   "PN",
   "SB3",
   "SC",
   "SP6",
   "WS"
  ],
  "hinweis": ""
 },
 "G71.3": {
  "diagnose": "Mitochondriale Myopathie, anderenorts nicht klassifiziert",
  "gruppen": [
   "EN1",
   "EN3",
   "PN",
   "SB3",
   "SC",
   "SP6",
   "ZN"
  ],
  "hinweis": ""
 },
 "G72.3": {
  "diagnose": "Periodische Lähmung",
  "gruppen": [
   "AT",
   "EN3",
   "PN",
   "SB3"
  ],
  "hinweis": ""
 },
 "G72.4": {
  "diagnose": "Entzündliche Myopathie, anderenorts nicht klassifiziert",
  "gruppen": [
   "AT",
   "EN3",
   "PN",
   "SC",
   "SP6"
  ],
  "hinweis": ""
 },
 "G80.0": {
  "diagnose": "Spastische tetraplegische Zerebralparese",
  "gruppen": [
   "SC",
   "SP6"
  ],
  "hinweis": ""
 },
 "G80.1": {
  "diagnose": "Spastische diplegische Zerebralparese",
  "gruppen": [
   "SC",
   "SP6"
  ],
  "hinweis": ""
 },
 "G80.2": {
  "diagnose": "Infantile hemiplegische Zerebralparese",
  "gruppen": [
   "SC",
   "SP6"
  ],
  "hinweis": ""
 },
 "G80.3": {
  "diagnose": "Dyskinetische Zerebralparese",
  "gruppen": [
   "SC",
   "SP6"
  ],
  "hinweis": ""
 },
 "G80.4": {
  "diagnose": "Ataktische Zerebralparese",
  "gruppen": [
   "SC",
   "SP6"
  ],
  "hinweis": ""
 },
 "G80.8": {
  "diagnose": "Sonstige infantile Zerebralparese",
  "gruppen": [
   "SC",
   "SP6"
  ],
  "hinweis": ""
 },
 "G80.9": {
  "diagnose": "Infantile Zerebralparese, nicht näher be- zeichnet",
  "gruppen": [
   "SC",
   "SP6"
  ],
  "hinweis": ""
 },
 "G81.0": {
  "diagnose": "Schlaffe Hemiparese und Hemiplegie",
  "gruppen": [
   "EN1",
   "ZN"
  ],
  "hinweis": ""
 },
 "G81.1": {
  "diagnose": "Spastische Hemiparese und Hemiplegie",
  "gruppen": [
   "EN1",
   "ZN"
  ],
  "hinweis": ""
 },
 "G93.1": {
  "diagnose": "Anoxische Hirnschädigung, anderenorts nicht klassifiziert",
  "gruppen": [
   "EN1",
   "SC",
   "ZN"
  ],
  "hinweis": "Wachkoma (apalli- sches Syndrom, auch infolge Hypoxie)"
 },
 "G93.80": {
  "diagnose": "Apallisches Syndrom",
  "gruppen": [
   "EN1",
   "SC",
   "ZN"
  ],
  "hinweis": "Wachkoma (apalli- sches Syndrom, auch infolge Hypoxie)"
 },
 "G95.0": {
  "diagnose": "Syringomyelie und Syringobulbie",
  "gruppen": [
   "EN1",
   "EN2",
   "ZN"
  ],
  "hinweis": ""
 },
 "I60.0": {
  "diagnose": "Subarachnoidalblutung, vom Karotis- siphon oder der Karotisbifurkation aus- gehend",
  "gruppen": [
   "EN1",
   "SC",
   "SP5",
   "SP6",
   "ST1",
   "ZN"
  ],
  "hinweis": "längstens 1 Jahr nach Akutereignis"
 },
 "I60.1": {
  "diagnose": "Subarachnoidalblutung, von der A. cerebri media ausgehend",
  "gruppen": [
   "EN1",
   "SC",
   "SP5",
   "SP6",
   "ST1",
   "ZN"
  ],
  "hinweis": "längstens 1 Jahr nach Akutereignis"
 },
 "I60.2": {
  "diagnose": "Subarachnoidalblutung, von der A. communicans anterior ausgehend",
  "gruppen": [
   "EN1",
   "SC",
   "SP5",
   "SP6",
   "ST1",
   "ZN"
  ],
  "hinweis": "längstens 1 Jahr nach Akutereignis"
 },
 "I60.3": {
  "diagnose": "Subarachnoidalblutung, von der A. communicans posterior ausgehend",
  "gruppen": [
   "EN1",
   "SC",
   "SP5",
   "SP6",
   "ST1",
   "ZN"
  ],
  "hinweis": "längstens 1 Jahr nach Akutereignis"
 },
 "I60.4": {
  "diagnose": "Subarachnoidalblutung, von der A. basilaris ausgehend",
  "gruppen": [
   "EN1",
   "SC",
   "SP5",
   "SP6",
   "ST1",
   "ZN"
  ],
  "hinweis": "längstens 1 Jahr nach Akutereignis"
 },
 "I60.5": {
  "diagnose": "Subarachnoidalblutung, von der A. verte- bralis ausgehend",
  "gruppen": [
   "EN1",
   "SC",
   "SP5",
   "SP6",
   "ST1",
   "ZN"
  ],
  "hinweis": "längstens 1 Jahr nach Akutereignis"
 },
 "I60.6": {
  "diagnose": "Subarachnoidalblutung, von sonstigen intrakraniellen Arterien ausgehend",
  "gruppen": [
   "EN1",
   "SC",
   "SP5",
   "SP6",
   "ST1",
   "ZN"
  ],
  "hinweis": "längstens 1 Jahr nach Akutereignis"
 },
 "I60.7": {
  "diagnose": "Subarachnoidalblutung, von nicht näher bezeichneter intrakranieller Arterie aus- gehend",
  "gruppen": [
   "EN1",
   "SC",
   "SP5",
   "SP6",
   "ST1",
   "ZN"
  ],
  "hinweis": "längstens 1 Jahr nach Akutereignis"
 },
 "I60.8": {
  "diagnose": "Sonstige Subarachnoidalblutung",
  "gruppen": [
   "EN1",
   "SC",
   "SP5",
   "SP6",
   "ST1",
   "ZN"
  ],
  "hinweis": "längstens 1 Jahr nach Akutereignis"
 },
 "I60.9": {
  "diagnose": "Subarachnoidalblutung, nicht näher be- zeichnet",
  "gruppen": [
   "EN1",
   "SC",
   "SP5",
   "SP6",
   "ST1",
   "ZN"
  ],
  "hinweis": "längstens 1 Jahr nach Akutereignis"
 },
 "I61.0": {
  "diagnose": "Intrazerebrale Blutung in die Großhirnhe- misphäre, subkortikal",
  "gruppen": [
   "EN1",
   "SC",
   "SP5",
   "SP6",
   "ST1",
   "ZN"
  ],
  "hinweis": "längstens 1 Jahr nach Akutereignis"
 },
 "I61.1": {
  "diagnose": "Intrazerebrale Blutung in die Großhirnhe- misphäre, kortikal",
  "gruppen": [
   "EN1",
   "SC",
   "SP5",
   "SP6",
   "ST1",
   "ZN"
  ],
  "hinweis": "längstens 1 Jahr nach Akutereignis"
 },
 "I61.2": {
  "diagnose": "Intrazerebrale Blutung in die Großhirnhe- misphäre, nicht näher bezeichnet",
  "gruppen": [
   "EN1",
   "SC",
   "SP5",
   "SP6",
   "ST1",
   "ZN"
  ],
  "hinweis": "längstens 1 Jahr nach Akutereignis"
 },
 "I61.3": {
  "diagnose": "Intrazerebrale Blutung in den Hirnstamm",
  "gruppen": [
   "EN1",
   "SC",
   "SP5",
   "SP6",
   "ST1",
   "ZN"
  ],
  "hinweis": "längstens 1 Jahr nach Akutereignis"
 },
 "I61.4": {
  "diagnose": "Intrazerebrale Blutung in das Kleinhirn",
  "gruppen": [
   "EN1",
   "SC",
   "SP5",
   "SP6",
   "ST1",
   "ZN"
  ],
  "hinweis": "längstens 1 Jahr nach Akutereignis"
 },
 "I61.5": {
  "diagnose": "Intrazerebrale intraventrikuläre Blutung",
  "gruppen": [
   "EN1",
   "SC",
   "SP5",
   "SP6",
   "ST1",
   "ZN"
  ],
  "hinweis": "längstens 1 Jahr nach Akutereignis"
 },
 "I61.6": {
  "diagnose": "Intrazerebrale Blutung an mehreren Lokalisationen",
  "gruppen": [
   "EN1",
   "SC",
   "SP5",
   "SP6",
   "ST1",
   "ZN"
  ],
  "hinweis": "längstens 1 Jahr nach Akutereignis"
 },
 "I61.8": {
  "diagnose": "Sonstige intrazerebrale Blutung",
  "gruppen": [
   "EN1",
   "SC",
   "SP5",
   "SP6",
   "ST1",
   "ZN"
  ],
  "hinweis": "längstens 1 Jahr nach Akutereignis"
 },
 "I61.9": {
  "diagnose": "Intrazerebrale Blutung, nicht näher be- zeichnet",
  "gruppen": [
   "EN1",
   "SC",
   "SP5",
   "SP6",
   "ST1",
   "ZN"
  ],
  "hinweis": "längstens 1 Jahr nach Akutereignis"
 },
 "I63.0": {
  "diagnose": "Hirninfarkt durch Thrombose präzerebra- ler Arterien",
  "gruppen": [
   "EN1",
   "SC",
   "SP5",
   "SP6",
   "ST1",
   "ZN"
  ],
  "hinweis": "längstens 1 Jahr nach Akutereignis"
 },
 "I63.1": {
  "diagnose": "Hirninfarkt durch Embolie präzerebraler Arterien",
  "gruppen": [
   "EN1",
   "SC",
   "SP5",
   "SP6",
   "ST1",
   "ZN"
  ],
  "hinweis": "längstens 1 Jahr nach Akutereignis"
 },
 "I63.2": {
  "diagnose": "Hirninfarkt durch nicht näher bezeichne- ten Verschluss oder Stenose präzerebra- ler Arterien",
  "gruppen": [
   "EN1",
   "SC",
   "SP5",
   "SP6",
   "ST1",
   "ZN"
  ],
  "hinweis": "längstens 1 Jahr nach Akutereignis"
 },
 "I63.3": {
  "diagnose": "Hirninfarkt durch Thrombose zerebraler Arterien",
  "gruppen": [
   "EN1",
   "SC",
   "SP5",
   "SP6",
   "ST1",
   "ZN"
  ],
  "hinweis": "längstens 1 Jahr nach Akutereignis"
 },
 "I63.4": {
  "diagnose": "Hirninfarkt durch Embolie zerebraler Arterien",
  "gruppen": [
   "EN1",
   "SC",
   "SP5",
   "SP6",
   "ST1",
   "ZN"
  ],
  "hinweis": "längstens 1 Jahr nach Akutereignis"
 },
 "I63.5": {
  "diagnose": "Hirninfarkt durch nicht näher bezeichne- ten Verschluss oder Stenose zerebraler Arterien",
  "gruppen": [
   "EN1",
   "SC",
   "SP5",
   "SP6",
   "ST1",
   "ZN"
  ],
  "hinweis": "längstens 1 Jahr nach Akutereignis"
 },
 "I63.6": {
  "diagnose": "Hirninfarkt durch Thrombose der Hirn- venen, nichteitrig",
  "gruppen": [
   "EN1",
   "SC",
   "SP5",
   "SP6",
   "ST1",
   "ZN"
  ],
  "hinweis": "längstens 1 Jahr nach Akutereignis"
 },
 "I63.8": {
  "diagnose": "Sonstiger Hirninfarkt",
  "gruppen": [
   "EN1",
   "SC",
   "SP5",
   "SP6",
   "ST1",
   "ZN"
  ],
  "hinweis": "längstens 1 Jahr nach Akutereignis"
 },
 "I63.9": {
  "diagnose": "Hirninfarkt, nicht näher bezeichnet",
  "gruppen": [
   "EN1",
   "SC",
   "SP5",
   "SP6",
   "ST1",
   "ZN"
  ],
  "hinweis": "längstens 1 Jahr nach Akutereignis"
 },
 "I64": {
  "diagnose": "Schlaganfall, nicht als Blutung oder In- farkt bezeichnet",
  "gruppen": [
   "EN1",
   "SC",
   "SP5",
   "SP6",
   "ST1",
   "ZN"
  ],
  "hinweis": "längstens 1 Jahr nach Akutereignis"
 },
 "I69.0": {
  "diagnose": "Folgen einer Subarachnoidalblutung",
  "gruppen": [
   "EN1",
   "SC",
   "SP5",
   "SP6",
   "ST1",
   "ZN"
  ],
  "hinweis": "längstens 1 Jahr nach Akutereignis"
 },
 "I69.1": {
  "diagnose": "Folgen einer intrazerebralen Blutung",
  "gruppen": [
   "EN1",
   "SC",
   "SP5",
   "SP6",
   "ST1",
   "ZN"
  ],
  "hinweis": "längstens 1 Jahr nach Akutereignis"
 },
 "I69.2": {
  "diagnose": "Folgen einer sonstigen nichttraumati- schen intrakraniellen Blutung",
  "gruppen": [
   "EN1",
   "SC",
   "SP5",
   "SP6",
   "ST1",
   "ZN"
  ],
  "hinweis": "längstens 1 Jahr nach Akutereignis"
 },
 "I69.3": {
  "diagnose": "Folgen eines Hirninfarktes",
  "gruppen": [
   "EN1",
   "SC",
   "SP5",
   "SP6",
   "ST1",
   "ZN"
  ],
  "hinweis": "längstens 1 Jahr nach Akutereignis"
 },
 "I69.4": {
  "diagnose": "Folgen eines Schlaganfalls, nicht als Blutung oder Infarkt bezeichnet",
  "gruppen": [
   "EN1",
   "SC",
   "SP5",
   "SP6",
   "ST1",
   "ZN"
  ],
  "hinweis": "längstens 1 Jahr nach Akutereignis"
 },
 "I69.8": {
  "diagnose": "Folgen sonstiger und nicht näher bezeich- neter zerebrovaskulärer Krankheiten",
  "gruppen": [
   "EN1",
   "SC",
   "SP5",
   "SP6",
   "ST1",
   "ZN"
  ],
  "hinweis": "längstens 1 Jahr nach Akutereignis"
 },
 "Q01.0": {
  "diagnose": "Frontale Enzephalozele",
  "gruppen": [
   "AT",
   "EN1",
   "SC",
   "SO1",
   "SO3",
   "SP1",
   "SP5",
   "SP6",
   "ZN"
  ],
  "hinweis": ""
 },
 "Q01.1": {
  "diagnose": "Nasofrontale Enzephalozele",
  "gruppen": [
   "AT",
   "EN1",
   "SC",
   "SO1",
   "SO3",
   "SP1",
   "SP5",
   "SP6",
   "ZN"
  ],
  "hinweis": ""
 },
 "Q01.2": {
  "diagnose": "Okzipitale Enzephalozele",
  "gruppen": [
   "AT",
   "EN1",
   "SC",
   "SO1",
   "SO3",
   "SP1",
   "SP5",
   "SP6",
   "ZN"
  ],
  "hinweis": ""
 },
 "Q01.8": {
  "diagnose": "Enzephalozele sonstiger Lokalisationen",
  "gruppen": [
   "AT",
   "EN1",
   "SC",
   "SO1",
   "SO3",
   "SP1",
   "SP5",
   "SP6",
   "ZN"
  ],
  "hinweis": ""
 },
 "Q01.9": {
  "diagnose": "Enzephalozele, nicht näher bezeichnet",
  "gruppen": [
   "AT",
   "EN1",
   "SC",
   "SO1",
   "SO3",
   "SP1",
   "SP5",
   "SP6",
   "ZN"
  ],
  "hinweis": ""
 },
 "Q03.0": {
  "diagnose": "Fehlbildungen des Aquaeductus cerebri",
  "gruppen": [
   "AT",
   "EN1",
   "SC",
   "SO1",
   "SO3",
   "SP1",
   "SP5",
   "SP6",
   "ZN"
  ],
  "hinweis": ""
 },
 "Q03.1": {
  "diagnose": "Atresie der Apertura mediana [Foramen Magendii] oder der Aperturae laterales [Foramina Luschkae] des vierten Ventri- kels",
  "gruppen": [
   "AT",
   "EN1",
   "SC",
   "SO1",
   "SO3",
   "SP1",
   "SP5",
   "SP6",
   "ZN"
  ],
  "hinweis": ""
 },
 "Q03.8": {
  "diagnose": "Sonstiger angeborener Hydrozephalus",
  "gruppen": [
   "AT",
   "EN1",
   "SC",
   "SO1",
   "SO3",
   "SP1",
   "SP5",
   "SP6",
   "ZN"
  ],
  "hinweis": ""
 },
 "Q03.9": {
  "diagnose": "Angeborener Hydrozephalus, nicht näher bezeichnet",
  "gruppen": [
   "AT",
   "EN1",
   "SC",
   "SO1",
   "SO3",
   "SP1",
   "SP5",
   "SP6",
   "ZN"
  ],
  "hinweis": ""
 },
 "Q04.0": {
  "diagnose": "Angeborene Fehlbildungen des Corpus callosum",
  "gruppen": [
   "AT",
   "EN1",
   "SC",
   "SO1",
   "SO3",
   "SP1",
   "SP5",
   "SP6",
   "ZN"
  ],
  "hinweis": ""
 },
 "Q04.1": {
  "diagnose": "Arrhinenzephalie",
  "gruppen": [
   "AT",
   "EN1",
   "SC",
   "SO1",
   "SO3",
   "SP1",
   "SP5",
   "SP6",
   "ZN"
  ],
  "hinweis": ""
 },
 "Q04.2": {
  "diagnose": "Holoprosenzephalie-Syndrom",
  "gruppen": [
   "AT",
   "EN1",
   "SC",
   "SO1",
   "SO3",
   "SP1",
   "SP5",
   "SP6",
   "ZN"
  ],
  "hinweis": ""
 },
 "Q04.3": {
  "diagnose": "Sonstige Reduktionsdeformitäten des Gehirns",
  "gruppen": [
   "AT",
   "EN1",
   "SC",
   "SO1",
   "SO3",
   "SP1",
   "SP5",
   "SP6",
   "ZN"
  ],
  "hinweis": ""
 },
 "Q04.4": {
  "diagnose": "Septooptische Dysplasie",
  "gruppen": [
   "AT",
   "EN1",
   "SC",
   "SO1",
   "SO3",
   "SP1",
   "SP5",
   "SP6",
   "ZN"
  ],
  "hinweis": ""
 },
 "Q04.5": {
  "diagnose": "Megalenzephalie",
  "gruppen": [
   "AT",
   "EN1",
   "SC",
   "SO1",
   "SO3",
   "SP1",
   "SP5",
   "SP6",
   "ZN"
  ],
  "hinweis": ""
 },
 "Q04.6": {
  "diagnose": "Angeborene Gehirnzysten",
  "gruppen": [
   "AT",
   "EN1",
   "SC",
   "SO1",
   "SO3",
   "SP1",
   "SP5",
   "SP6",
   "ZN"
  ],
  "hinweis": ""
 },
 "Q04.8": {
  "diagnose": "Sonstige näher bezeichnete angeborene Fehlbildungen des Gehirns",
  "gruppen": [
   "AT",
   "EN1",
   "SC",
   "SO1",
   "SO3",
   "SP1",
   "SP5",
   "SP6",
   "ZN"
  ],
  "hinweis": ""
 },
 "Q04.9": {
  "diagnose": "Angeborene Fehlbildung des Gehirns, nicht näher bezeichnet",
  "gruppen": [
   "AT",
   "EN1",
   "SC",
   "SO1",
   "SO3",
   "SP1",
   "SP5",
   "SP6",
   "ZN"
  ],
  "hinweis": ""
 },
 "Q05.0": {
  "diagnose": "Zervikale Spina bifida mit Hydrozephalus",
  "gruppen": [
   "AT",
   "EN1",
   "EN2",
   "SC",
   "SO1",
   "SO3",
   "SP1",
   "SP5",
   "SP6",
   "ZN"
  ],
  "hinweis": ""
 },
 "Q05.1": {
  "diagnose": "Thorakale Spina bifida mit Hydrozephalus",
  "gruppen": [
   "AT",
   "EN1",
   "EN2",
   "SC",
   "SO1",
   "SO3",
   "SP1",
   "SP5",
   "SP6",
   "ZN"
  ],
  "hinweis": ""
 },
 "Q05.2": {
  "diagnose": "Lumbale Spina bifida mit Hydrozephalus",
  "gruppen": [
   "AT",
   "EN1",
   "EN2",
   "SC",
   "SO1",
   "SO3",
   "SP1",
   "SP5",
   "SP6",
   "ZN"
  ],
  "hinweis": ""
 },
 "Q05.3": {
  "diagnose": "Sakrale Spina bifida mit Hydrozephalus",
  "gruppen": [
   "AT",
   "EN1",
   "EN2",
   "SC",
   "SO1",
   "SO3",
   "SP1",
   "SP5",
   "SP6",
   "ZN"
  ],
  "hinweis": ""
 },
 "Q05.4": {
  "diagnose": "Nicht näher bezeichnete Spina bifida mit Hydrozephalus",
  "gruppen": [
   "AT",
   "EN1",
   "EN2",
   "SC",
   "SO1",
   "SO3",
   "SP1",
   "SP5",
   "SP6",
   "ZN"
  ],
  "hinweis": ""
 },
 "Q05.5": {
  "diagnose": "Zervikale Spina bifida ohne Hydrozepha- lus",
  "gruppen": [
   "AT",
   "EN1",
   "EN2",
   "SC",
   "SO1",
   "SO3",
   "SP1",
   "SP5",
   "SP6",
   "ZN"
  ],
  "hinweis": ""
 },
 "Q05.6": {
  "diagnose": "Thorakale Spina bifida ohne Hydroze- phalus",
  "gruppen": [
   "AT",
   "EN1",
   "EN2",
   "SC",
   "SO1",
   "SO3",
   "SP1",
   "SP5",
   "SP6",
   "ZN"
  ],
  "hinweis": ""
 },
 "Q05.7": {
  "diagnose": "Lumbale Spina bifida ohne Hydrozepha- lus",
  "gruppen": [
   "AT",
   "EN1",
   "EN2",
   "SC",
   "SO1",
   "SO3",
   "SP1",
   "SP5",
   "SP6",
   "ZN"
  ],
  "hinweis": ""
 },
 "Q05.8": {
  "diagnose": "Sakrale Spina bifida ohne Hydrozephalus",
  "gruppen": [
   "AT",
   "EN1",
   "EN2",
   "SC",
   "SO1",
   "SO3",
   "SP1",
   "SP5",
   "SP6",
   "ZN"
  ],
  "hinweis": ""
 },
 "Q05.9": {
  "diagnose": "Spina bifida, nicht näher bezeichnet",
  "gruppen": [
   "AT",
   "EN1",
   "EN2",
   "SC",
   "SO1",
   "SO3",
   "SP1",
   "SP5",
   "SP6",
   "ZN"
  ],
  "hinweis": ""
 },
 "Q06.0": {
  "diagnose": "Amyelie",
  "gruppen": [
   "AT",
   "EN2",
   "SC",
   "SO1",
   "SO3",
   "SP1",
   "SP6",
   "ZN"
  ],
  "hinweis": ""
 },
 "Q06.1": {
  "diagnose": "Hypoplasie und Dysplasie des Rücken- markes",
  "gruppen": [
   "AT",
   "EN2",
   "SC",
   "SO1",
   "SO3",
   "SP1",
   "SP6",
   "ZN"
  ],
  "hinweis": ""
 },
 "Q06.2": {
  "diagnose": "Diastematomyelie",
  "gruppen": [
   "AT",
   "EN2",
   "SC",
   "SO1",
   "SO3",
   "SP1",
   "SP6",
   "ZN"
  ],
  "hinweis": ""
 },
 "Q06.3": {
  "diagnose": "Sonstige angeborene Fehlbildungen der Cauda equina",
  "gruppen": [
   "AT",
   "EN2",
   "SC",
   "SO1",
   "SO3",
   "SP1",
   "SP6",
   "ZN"
  ],
  "hinweis": ""
 },
 "Q06.4": {
  "diagnose": "Hydromyelie",
  "gruppen": [
   "AT",
   "EN2",
   "SC",
   "SO1",
   "SO3",
   "SP1",
   "SP6",
   "ZN"
  ],
  "hinweis": ""
 },
 "Q06.8": {
  "diagnose": "Sonstige näher bezeichnete angeborene Fehlbildungen des Rückenmarkes",
  "gruppen": [
   "AT",
   "EN2",
   "SC",
   "SO1",
   "SO3",
   "SP1",
   "SP6",
   "ZN"
  ],
  "hinweis": ""
 },
 "Q06.9": {
  "diagnose": "Angeborene Fehlbildung des Rückenmar- kes, nicht näher bezeichnet",
  "gruppen": [
   "AT",
   "EN2",
   "SC",
   "SO1",
   "SO3",
   "SP1",
   "SP6",
   "ZN"
  ],
  "hinweis": ""
 },
 "S14.0": {
  "diagnose": "Kontusion und Ödem des zervikalen Rückenmarkes",
  "gruppen": [
   "AT",
   "EN1",
   "EN2",
   "ZN"
  ],
  "hinweis": "längstens 1 Jahr nach Akutereignis"
 },
 "S14.2": {
  "diagnose": "Verletzung von Nervenwurzeln der Hals- wirbelsäule",
  "gruppen": [],
  "hinweis": ""
 },
 "S14.3": {
  "diagnose": "Verletzung des Plexus brachialis",
  "gruppen": [
   "AT",
   "EN1",
   "EN2",
   "ZN"
  ],
  "hinweis": "längstens 1 Jahr nach Akutereignis"
 },
 "S14.4": {
  "diagnose": "Verletzung peripherer Nerven des Halses",
  "gruppen": [
   "EN3"
  ],
  "hinweis": ""
 },
 "S14.5": {
  "diagnose": "Verletzung zervikaler sympathischer Nerven",
  "gruppen": [
   "AT",
   "EN1",
   "EN2",
   "ZN"
  ],
  "hinweis": "längstens 1 Jahr nach Akutereignis"
 },
 "S14.6": {
  "diagnose": "Verletzung sonstiger und nicht näher be- zeichneter Nerven des Halses",
  "gruppen": [
   "AT",
   "EN1",
   "EN2",
   "ZN"
  ],
  "hinweis": "längstens 1 Jahr nach Akutereignis"
 },
 "S24.0": {
  "diagnose": "Kontusion und Ödem des thorakalen Rückenmarkes",
  "gruppen": [
   "EN1",
   "EN2",
   "ZN"
  ],
  "hinweis": "längstens 1 Jahr nach Akutereignis"
 },
 "S24.2": {
  "diagnose": "Verletzung von Nervenwurzeln der Brust- wirbelsäule",
  "gruppen": [],
  "hinweis": ""
 },
 "S24.3": {
  "diagnose": "Verletzung peripherer Nerven des Thorax",
  "gruppen": [],
  "hinweis": ""
 },
 "S24.4": {
  "diagnose": "Verletzung thorakaler sympathischer Nerven",
  "gruppen": [],
  "hinweis": ""
 },
 "S24.5": {
  "diagnose": "Verletzung sonstiger Nerven des Thorax",
  "gruppen": [],
  "hinweis": ""
 },
 "S24.6": {
  "diagnose": "Verletzung eines nicht näher bezeichne- ten Nervs des Thorax",
  "gruppen": [],
  "hinweis": ""
 },
 "S34.0": {
  "diagnose": "Kontusion und Ödem des lumbalen Rü- ckenmarkes [Conus medullaris]",
  "gruppen": [
   "EN1",
   "EN2",
   "ZN"
  ],
  "hinweis": "längstens 1 Jahr nach Akutereignis"
 },
 "S34.2": {
  "diagnose": "Verletzung von Nervenwurzeln der Len- denwirbelsäule und des Kreuzbeins",
  "gruppen": [
   "EN1",
   "EN2",
   "ZN"
  ],
  "hinweis": "längstens 1 Jahr nach Akutereignis"
 },
 "S34.4": {
  "diagnose": "Verletzung des Plexus lumbosacralis",
  "gruppen": [],
  "hinweis": ""
 },
 "S34.5": {
  "diagnose": "Verletzung sympathischer Nerven der Lendenwirbel-, Kreuzbein- und Becken- region",
  "gruppen": [],
  "hinweis": ""
 },
 "S34.6": {
  "diagnose": "Verletzung eines oder mehrerer periphe- rer Nerven des Abdomens, der Lumbosa- kralgegend und des Beckens",
  "gruppen": [],
  "hinweis": ""
 },
 "S34.8": {
  "diagnose": "Verletzung sonstiger und nicht näher bezeichneter Nerven in Höhe des Abdo- mens, der Lumbosakralgegend und des Beckens",
  "gruppen": [],
  "hinweis": ""
 },
 "T09.3": {
  "diagnose": "Verletzung des Rückenmarkes, Höhe nicht näher bezeichnet",
  "gruppen": [
   "AT",
   "EN2",
   "ZN"
  ],
  "hinweis": "längstens 1 Jahr nach Akutereignis"
 },
 "T90.5": {
  "diagnose": "Folgen einer intrakraniellen Verletzung",
  "gruppen": [
   "AT",
   "EN1",
   "SC",
   "SO3",
   "ZN"
  ],
  "hinweis": "Folgen einer Ver- letzung, die unter S06.- klassifizierbar ist: - nicht umfasst: S06.0 Gehirner- schütterung - umfasst: S06.1 bis S06.9 Hinweis: Folgen oder Spätfolgen, die ein Jahr oder länger nach der akuten Verletzung bestehen"
 },
 "M42.04": {
  "diagnose": "Juvenile Osteochondrose der Wirbelsäule (Thorakalbereich)",
  "gruppen": [
   "WS"
  ],
  "hinweis": "fixierte Kyphose ab Gesamtkyphose- winkel über 40° bei Kindern bis zum vollendeten 18. Lebensjahr"
 },
 "M42.05": {
  "diagnose": "Juvenile Osteochondrose der Wirbelsäule (Thorakolumbalbereich)",
  "gruppen": [
   "WS"
  ],
  "hinweis": "fixierte Kyphose ab Gesamtkyphose- winkel über 40° bei Kindern bis zum vollendeten 18. Lebensjahr"
 },
 "G99.2": {
  "diagnose": "Arteria-spinalis-anterior-Kompressions- syndrom und Arteria-vertebralis-Kompres- sionssyndrom mit Myelopathie",
  "gruppen": [
   "EN2",
   "EX",
   "WS",
   "ZN"
  ],
  "hinweis": "längstens 6 Monate nach Akutereignis Voraussetzung für die Anerkennung als besonderer Ver- ordnungsbedarf ist die Angabe beider ICD-10-Diagno- seschlüssel"
 },
 "G55.2": {
  "diagnose": "Sonstige Spondylose mit Radikulopathie",
  "gruppen": [
   "EN2",
   "EX",
   "WS",
   "ZN"
  ],
  "hinweis": "längstens 6 Monate nach Akutereignis Voraussetzung für die Anerkennung als besonderer Ver- ordnungsbedarf ist die Angabe beider ICD-10-Diagno- seschlüssel"
 },
 "G55.3": {
  "diagnose": "Spinalkanalstenose mit Radikulopathie",
  "gruppen": [
   "EN2",
   "EX",
   "WS",
   "ZN"
  ],
  "hinweis": "längstens 6 Monate nach Akutereignis Voraussetzung für die Anerkennung als besonderer Ver- ordnungsbedarf ist die Angabe beider ICD-10-Diagno- seschlüssel"
 },
 "M50.0": {
  "diagnose": "Zervikaler Bandscheibenschaden mit Myelopathie",
  "gruppen": [
   "EN2",
   "EX",
   "WS",
   "ZN"
  ],
  "hinweis": "längstens 6 Monate nach Akutereignis Voraussetzung für die Anerkennung als besonderer Ver- ordnungsbedarf ist die Angabe beider ICD-10-Diagno- seschlüssel"
 },
 "M50.1": {
  "diagnose": "Zervikaler Bandscheibenschaden mit Radikulopathie",
  "gruppen": [
   "EN2",
   "EX",
   "WS",
   "ZN"
  ],
  "hinweis": "längstens 6 Monate nach Akutereignis Voraussetzung für die Anerkennung als besonderer Ver- ordnungsbedarf ist die Angabe beider ICD-10-Diagno- seschlüssel"
 },
 "G55.1": {
  "diagnose": "Zervikaler Bandscheibenschaden mit Radikulopathie",
  "gruppen": [
   "EN2",
   "EX",
   "WS",
   "ZN"
  ],
  "hinweis": "längstens 6 Monate nach Akutereignis Voraussetzung für die Anerkennung als besonderer Ver- ordnungsbedarf ist die Angabe beider ICD-10-Diagno- seschlüssel"
 },
 "M51.0": {
  "diagnose": "Lumbale und sonstige Bandscheiben- schäden mit Myelopathie",
  "gruppen": [
   "EN2",
   "EX",
   "WS",
   "ZN"
  ],
  "hinweis": "längstens 6 Monate nach Akutereignis Voraussetzung für die Anerkennung als besonderer Ver- ordnungsbedarf ist die Angabe beider ICD-10-Diagno- seschlüssel"
 },
 "M51.1": {
  "diagnose": "Lumbale und sonstige Bandscheiben- schäden mit Radikulopathie",
  "gruppen": [
   "EN2",
   "EX",
   "WS",
   "ZN"
  ],
  "hinweis": "längstens 6 Monate nach Akutereignis Voraussetzung für die Anerkennung als besonderer Ver- ordnungsbedarf ist die Angabe beider ICD-10-Diagno- seschlüssel"
 },
 "M75.1": {
  "diagnose": "Läsionen der Rotatorenmanschette",
  "gruppen": [
   "EX"
  ],
  "hinweis": ""
 },
 "Z89.1": {
  "diagnose": "Einseitiger Verlust der Hand und des Handgelenks",
  "gruppen": [
   "CS",
   "EX",
   "LY",
   "SB2",
   "WS"
  ],
  "hinweis": "längstens 12 Monate nach Akutereignis"
 },
 "Z89.2": {
  "diagnose": "Einseitiger Verlust der oberen Extremität (oberhalb des Handgelenkes)",
  "gruppen": [
   "CS",
   "EX",
   "LY",
   "SB2",
   "WS"
  ],
  "hinweis": "längstens 12 Monate nach Akutereignis"
 },
 "Z89.5": {
  "diagnose": "Einseitiger Verlust der unteren Extremität unterhalb oder bis zum Knie",
  "gruppen": [
   "CS",
   "EX",
   "LY",
   "SB2",
   "WS"
  ],
  "hinweis": "längstens 12 Monate nach Akutereignis"
 },
 "Z89.6": {
  "diagnose": "Einseitiger Verlust der unteren Extremität (oberhalb des Knies)",
  "gruppen": [
   "CS",
   "EX",
   "LY",
   "SB2",
   "WS"
  ],
  "hinweis": "längstens 12 Monate nach Akutereignis"
 },
 "Z89.3": {
  "diagnose": "Beidseitiger (teilweiser) Verlust der obe- ren Extremitäten",
  "gruppen": [
   "CS",
   "EX",
   "LY",
   "SB2",
   "WS"
  ],
  "hinweis": ""
 },
 "Z89.7": {
  "diagnose": "Beidseitiger (teilweiser) Verlust der unte- ren Extremitäten",
  "gruppen": [
   "CS",
   "EX",
   "LY",
   "SB2",
   "WS"
  ],
  "hinweis": ""
 },
 "Z89.8": {
  "diagnose": "Verlust der oberen und unteren Extremi- täten [jede Höhe]",
  "gruppen": [
   "CS",
   "EX",
   "LY",
   "SB2",
   "WS"
  ],
  "hinweis": ""
 },
 "M07.2": {
  "diagnose": "Spondylitis psoriatica",
  "gruppen": [],
  "hinweis": ""
 },
 "M08.3": {
  "diagnose": "Juvenile chronische Arthritis (seronega- tiv), polyartikuläre Form",
  "gruppen": [],
  "hinweis": ""
 },
 "M30.0": {
  "diagnose": "Panarteriitis nodosa",
  "gruppen": [
   "EN1",
   "EX",
   "PN",
   "SB1",
   "SB3",
   "SC",
   "ZN"
  ],
  "hinweis": ""
 },
 "M31.3": {
  "diagnose": "Granulomatose mit Polyangiitis*",
  "gruppen": [
   "EN1",
   "EX",
   "PN",
   "SB1",
   "SB3",
   "SC",
   "ZN"
  ],
  "hinweis": ""
 },
 "M32.1": {
  "diagnose": "Systemischer Lupus erythematodes mit Beteiligung von Organen oder Organsys- temen",
  "gruppen": [
   "AT",
   "EX",
   "SB1",
   "SB3",
   "WS"
  ],
  "hinweis": ""
 },
 "M32.8": {
  "diagnose": "Sonstige Formen des systemischen Lupus erythematodes",
  "gruppen": [
   "AT",
   "EX",
   "SB1",
   "SB3",
   "WS"
  ],
  "hinweis": ""
 },
 "M33.0": {
  "diagnose": "Juvenile Dermatomyositis",
  "gruppen": [
   "EN1",
   "EX",
   "PN",
   "SB1",
   "SB3",
   "SC",
   "ZN"
  ],
  "hinweis": ""
 },
 "M33.1": {
  "diagnose": "Sonstige Dermatomyositis",
  "gruppen": [
   "EN1",
   "EX",
   "PN",
   "SB1",
   "SB3",
   "SC",
   "ZN"
  ],
  "hinweis": ""
 },
 "M33.2": {
  "diagnose": "Polymyositis",
  "gruppen": [
   "EN1",
   "EX",
   "PN",
   "SB1",
   "SB3",
   "SC",
   "ZN"
  ],
  "hinweis": ""
 },
 "M34.0": {
  "diagnose": "Progressive systemische Sklerose",
  "gruppen": [
   "AT",
   "EX",
   "SB1",
   "SB3",
   "WS"
  ],
  "hinweis": ""
 },
 "M34.1": {
  "diagnose": "CR(E)ST-Syndrom",
  "gruppen": [
   "AT",
   "EX",
   "SB1",
   "SB3",
   "WS"
  ],
  "hinweis": ""
 },
 "M34.2": {
  "diagnose": "Systemische Sklerose, durch Arzneimittel oder chemische Substanzen induziert",
  "gruppen": [
   "AT",
   "EX",
   "SB1",
   "SB3",
   "WS"
  ],
  "hinweis": ""
 },
 "M34.8": {
  "diagnose": "Sonstige Formen der systemischen Sklerose",
  "gruppen": [
   "AT",
   "EX",
   "SB1",
   "SB3",
   "WS"
  ],
  "hinweis": ""
 },
 "M34.9": {
  "diagnose": "Systemische Sklerose, nicht näher be- zeichnet",
  "gruppen": [
   "AT",
   "EX",
   "SB1",
   "SB3",
   "WS"
  ],
  "hinweis": ""
 },
 "M36.2": {
  "diagnose": "Arthropathia haemophilica",
  "gruppen": [
   "CS",
   "EX",
   "SB1"
  ],
  "hinweis": ""
 },
 "Q79.6": {
  "diagnose": "Ehlers-Danlos-Syndrom",
  "gruppen": [
   "CS",
   "EX",
   "SB1",
   "SB2",
   "WS"
  ],
  "hinweis": ""
 },
 "Q87.4": {
  "diagnose": "Marfan-Syndrom",
  "gruppen": [
   "AT",
   "EX",
   "SB1",
   "SB3",
   "WS"
  ],
  "hinweis": ""
 },
 "Q66.0": {
  "diagnose": "Pes equinovarus congenitus (Klumpfuß)",
  "gruppen": [
   "EX",
   "SB2"
  ],
  "hinweis": ""
 },
 "Q68.0": {
  "diagnose": "Angeborene Deformitäten des M. sternoc- leidomastoideus",
  "gruppen": [
   "EX",
   "SB3"
  ],
  "hinweis": ""
 },
 "Q71.0": {
  "diagnose": "Angeborenes vollständiges Fehlen der oberen Extremität(en)",
  "gruppen": [
   "AT",
   "CS",
   "EX",
   "GE",
   "LY",
   "PN",
   "SB2",
   "SO1",
   "SO2",
   "SO3",
   "SO4",
   "WS",
   "ZN"
  ],
  "hinweis": ""
 },
 "Q71.1": {
  "diagnose": "Angeborenes Fehlen des Ober- und Unter- armes bei vorhandener Hand",
  "gruppen": [
   "AT",
   "CS",
   "EX",
   "GE",
   "LY",
   "PN",
   "SB2",
   "SO1",
   "SO2",
   "SO3",
   "SO4",
   "WS",
   "ZN"
  ],
  "hinweis": ""
 },
 "Q71.2": {
  "diagnose": "Angeborenes Fehlen sowohl des Unter- armes als auch der Hand",
  "gruppen": [
   "AT",
   "CS",
   "EX",
   "GE",
   "LY",
   "PN",
   "SB2",
   "SO1",
   "SO2",
   "SO3",
   "SO4",
   "WS",
   "ZN"
  ],
  "hinweis": ""
 },
 "Q71.3": {
  "diagnose": "Angeborenes Fehlen der Hand oder eines oder mehrerer Finger",
  "gruppen": [
   "AT",
   "CS",
   "EX",
   "GE",
   "LY",
   "PN",
   "SB2",
   "SO1",
   "SO2",
   "SO3",
   "SO4",
   "WS",
   "ZN"
  ],
  "hinweis": ""
 },
 "Q71.4": {
  "diagnose": "Longitudinaler Reduktionsdefekt des Radius",
  "gruppen": [
   "AT",
   "CS",
   "EX",
   "GE",
   "LY",
   "PN",
   "SB2",
   "SO1",
   "SO2",
   "SO3",
   "SO4",
   "WS",
   "ZN"
  ],
  "hinweis": ""
 },
 "Q71.5": {
  "diagnose": "Longitudinaler Reduktionsdefekt der Ulna",
  "gruppen": [
   "AT",
   "CS",
   "EX",
   "GE",
   "LY",
   "PN",
   "SB2",
   "SO1",
   "SO2",
   "SO3",
   "SO4",
   "WS",
   "ZN"
  ],
  "hinweis": ""
 },
 "Q71.6": {
  "diagnose": "Spalthand",
  "gruppen": [
   "AT",
   "CS",
   "EX",
   "GE",
   "LY",
   "PN",
   "SB2",
   "SO1",
   "SO2",
   "SO3",
   "SO4",
   "WS",
   "ZN"
  ],
  "hinweis": ""
 },
 "Q71.8": {
  "diagnose": "Sonstige Reduktionsdefekte der oberen Extremität(en)",
  "gruppen": [
   "AT",
   "CS",
   "EX",
   "GE",
   "LY",
   "PN",
   "SB2",
   "SO1",
   "SO2",
   "SO3",
   "SO4",
   "WS",
   "ZN"
  ],
  "hinweis": ""
 },
 "Q71.9": {
  "diagnose": "Reduktionsdefekt der oberen Extremität, nicht näher bezeichnet",
  "gruppen": [
   "AT",
   "CS",
   "EX",
   "GE",
   "LY",
   "PN",
   "SB2",
   "SO1",
   "SO2",
   "SO3",
   "SO4",
   "WS",
   "ZN"
  ],
  "hinweis": ""
 },
 "Q72.0": {
  "diagnose": "Angeborenes vollständiges Fehlen der unteren Extremität(en)",
  "gruppen": [
   "AT",
   "CS",
   "EX",
   "GE",
   "LY",
   "PN",
   "SB2",
   "SO1",
   "SO2",
   "SO3",
   "SO4",
   "WS",
   "ZN"
  ],
  "hinweis": ""
 },
 "Q72.1": {
  "diagnose": "Angeborenes Fehlen des Ober- und Unter- schenkels bei vorhandenem Fuß",
  "gruppen": [
   "AT",
   "CS",
   "EX",
   "GE",
   "LY",
   "PN",
   "SB2",
   "SO1",
   "SO2",
   "SO3",
   "SO4",
   "WS",
   "ZN"
  ],
  "hinweis": ""
 },
 "Q72.2": {
  "diagnose": "Angeborenes Fehlen sowohl des Unter- schenkels als auch des Fußes",
  "gruppen": [
   "AT",
   "CS",
   "EX",
   "GE",
   "LY",
   "PN",
   "SB2",
   "SO1",
   "SO2",
   "SO3",
   "SO4",
   "WS",
   "ZN"
  ],
  "hinweis": ""
 },
 "Q72.3": {
  "diagnose": "Angeborenes Fehlen des Fußes oder einer oder mehrerer Zehen",
  "gruppen": [
   "AT",
   "CS",
   "EX",
   "GE",
   "LY",
   "PN",
   "SB2",
   "SO1",
   "SO2",
   "SO3",
   "SO4",
   "WS",
   "ZN"
  ],
  "hinweis": ""
 },
 "Q72.4": {
  "diagnose": "Longitudinaler Reduktionsdefekt des Femurs",
  "gruppen": [
   "AT",
   "CS",
   "EX",
   "GE",
   "LY",
   "PN",
   "SB2",
   "SO1",
   "SO2",
   "SO3",
   "SO4",
   "WS",
   "ZN"
  ],
  "hinweis": ""
 },
 "Q72.5": {
  "diagnose": "Longitudinaler Reduktionsdefekt der Tibia",
  "gruppen": [
   "AT",
   "CS",
   "EX",
   "GE",
   "LY",
   "PN",
   "SB2",
   "SO1",
   "SO2",
   "SO3",
   "SO4",
   "WS",
   "ZN"
  ],
  "hinweis": ""
 },
 "Q72.6": {
  "diagnose": "Longitudinaler Reduktionsdefekt der Fibula",
  "gruppen": [
   "AT",
   "CS",
   "EX",
   "GE",
   "LY",
   "PN",
   "SB2",
   "SO1",
   "SO2",
   "SO3",
   "SO4",
   "WS",
   "ZN"
  ],
  "hinweis": ""
 },
 "Q72.7": {
  "diagnose": "Spaltfuß",
  "gruppen": [
   "AT",
   "CS",
   "EX",
   "GE",
   "LY",
   "PN",
   "SB2",
   "SO1",
   "SO2",
   "SO3",
   "SO4",
   "WS",
   "ZN"
  ],
  "hinweis": ""
 },
 "Q72.8": {
  "diagnose": "Sonstige Reduktionsdefekte der unteren Extremität(en)",
  "gruppen": [
   "AT",
   "CS",
   "EX",
   "GE",
   "LY",
   "PN",
   "SB2",
   "SO1",
   "SO2",
   "SO3",
   "SO4",
   "WS",
   "ZN"
  ],
  "hinweis": ""
 },
 "Q72.9": {
  "diagnose": "Reduktionsdefekt der unteren Extremität, nicht näher bezeichnet",
  "gruppen": [
   "AT",
   "CS",
   "EX",
   "GE",
   "LY",
   "PN",
   "SB2",
   "SO1",
   "SO2",
   "SO3",
   "SO4",
   "WS",
   "ZN"
  ],
  "hinweis": ""
 },
 "Q73.0": {
  "diagnose": "Angeborenes Fehlen nicht näher bezeich- neter Extremität(en)",
  "gruppen": [],
  "hinweis": ""
 },
 "Q73.1": {
  "diagnose": "Phokomelie nicht näher bezeichneter Extremität(en)",
  "gruppen": [],
  "hinweis": ""
 },
 "Q73.8": {
  "diagnose": "Sonstige Reduktionsdefekte nicht näher bezeichneter Extremität(en)",
  "gruppen": [
   "AT",
   "CS",
   "EX",
   "GE",
   "LY",
   "PN",
   "SB2",
   "SO1",
   "SO2",
   "SO3",
   "SO4",
   "WS",
   "ZN"
  ],
  "hinweis": ""
 },
 "Q74.3": {
  "diagnose": "Arthrogryposis multiplex congenita",
  "gruppen": [
   "EX",
   "SB1"
  ],
  "hinweis": ""
 },
 "Q78.0": {
  "diagnose": "Osteogenesis imperfecta",
  "gruppen": [
   "EX",
   "SB1",
   "WS"
  ],
  "hinweis": ""
 },
 "Q86.80": {
  "diagnose": "Thalidomid-Embryopathie",
  "gruppen": [
   "SP3",
   "SP4",
   "SP6"
  ],
  "hinweis": ""
 },
 "Q87.0": {
  "diagnose": "Angeborene Fehlbildungssyndrome mit vorwiegender Beteiligung des Gesichtes",
  "gruppen": [
   "EX",
   "SB2",
   "SC",
   "SF",
   "SP3",
   "WS"
  ],
  "hinweis": ""
 },
 "Q87.2": {
  "diagnose": "Angeborene Fehlbildungssyndrome mit vorwiegender Beteiligung der Extremi- täten",
  "gruppen": [
   "CS",
   "EX",
   "LY",
   "SB1",
   "SB2"
  ],
  "hinweis": ""
 },
 "Z98.88": {
  "diagnose": "Chronische Instabilität des Kniegelenks",
  "gruppen": [
   "EX",
   "LY",
   "SB2"
  ],
  "hinweis": "längstens 6 Monate nach Akutereignis Voraussetzung für die Anerkennung als besonderer Ver- ordnungsbedarf ist die Angabe beider ICD-10-Diagno- seschlüssel"
 },
 "M24.41": {
  "diagnose": "Habituelle Luxation und Subluxation eines Gelenkes: Schulterregion",
  "gruppen": [
   "EX",
   "SB2"
  ],
  "hinweis": ""
 },
 "Z96.60": {
  "diagnose": "Vorhandensein einer Schulterprothese",
  "gruppen": [
   "EX",
   "SB2"
  ],
  "hinweis": ""
 },
 "Z96.64": {
  "diagnose": "Vorhandensein einer Hüftgelenkprothese",
  "gruppen": [
   "EX",
   "LY",
   "SB2"
  ],
  "hinweis": ""
 },
 "Z96.65": {
  "diagnose": "Vorhandensein einer Kniegelenkprothese",
  "gruppen": [
   "EX",
   "LY",
   "SB2"
  ],
  "hinweis": ""
 },
 "I89.01": {
  "diagnose": "Lymphödem der oberen und unteren Extremität(en), Stadium II",
  "gruppen": [
   "LY"
  ],
  "hinweis": ""
 },
 "I89.02": {
  "diagnose": "Lymphödem der oberen und unteren Extremität(en), Stadium III",
  "gruppen": [
   "LY"
  ],
  "hinweis": ""
 },
 "I89.04": {
  "diagnose": "Lymphödem, sonstige Lokalisation, Stadium II",
  "gruppen": [
   "LY"
  ],
  "hinweis": ""
 },
 "I89.05": {
  "diagnose": "Lymphödem, sonstige Lokalisation, Stadium III",
  "gruppen": [
   "LY"
  ],
  "hinweis": ""
 },
 "I97.21": {
  "diagnose": "Lymphödem nach (partieller) Mastekto- mie (mit Lymphadenektomie), Stadium II",
  "gruppen": [
   "LY"
  ],
  "hinweis": ""
 },
 "I97.22": {
  "diagnose": "Lymphödem nach (partieller) Mastekto- mie (mit Lymphadenektomie), Stadium III",
  "gruppen": [
   "LY"
  ],
  "hinweis": ""
 },
 "I97.82": {
  "diagnose": "Lymphödem nach medizinischen Maß- nahmen am axillären Lymphabflussge- biet, Stadium II",
  "gruppen": [
   "LY"
  ],
  "hinweis": ""
 },
 "I97.83": {
  "diagnose": "Lymphödem nach medizinischen Maß- nahmen am axillären Lymphabflussge- biet, Stadium III",
  "gruppen": [
   "LY"
  ],
  "hinweis": ""
 },
 "I97.85": {
  "diagnose": "Lymphödem nach medizinischen Maß- nahmen am inguinalen Lymphabflussge- biet, Stadium II",
  "gruppen": [
   "LY"
  ],
  "hinweis": ""
 },
 "I97.86": {
  "diagnose": "Lymphödem nach medizinischen Maß- nahmen am inguinalen Lymphabflussge- biet, Stadium III",
  "gruppen": [
   "LY"
  ],
  "hinweis": ""
 },
 "Q82.01": {
  "diagnose": "Hereditäres Lymphödem der oberen und unteren Extremität(en), Stadium II",
  "gruppen": [
   "LY"
  ],
  "hinweis": ""
 },
 "Q82.02": {
  "diagnose": "Hereditäres Lymphödem der oberen und unteren Extremität(en), Stadium III",
  "gruppen": [
   "LY"
  ],
  "hinweis": ""
 },
 "Q82.04": {
  "diagnose": "Hereditäres Lymphödem, sonstige Lokali- sation, Stadium II",
  "gruppen": [
   "LY"
  ],
  "hinweis": ""
 },
 "Q82.05": {
  "diagnose": "Hereditäres Lymphödem, sonstige Lokali- sation, Stadium III",
  "gruppen": [
   "LY"
  ],
  "hinweis": ""
 },
 "Q37.0": {
  "diagnose": "Spalte des harten Gaumens mit beidseiti- ger Lippenspalte",
  "gruppen": [
   "SF",
   "SP3"
  ],
  "hinweis": ""
 },
 "Q37.1": {
  "diagnose": "Spalte des harten Gaumens mit einseiti- ger Lippenspalte",
  "gruppen": [
   "SF",
   "SP3"
  ],
  "hinweis": ""
 },
 "Q37.2": {
  "diagnose": "Spalte des weichen Gaumens mit beidsei- tiger Lippenspalte",
  "gruppen": [
   "SF",
   "SP3"
  ],
  "hinweis": ""
 },
 "Q37.3": {
  "diagnose": "Spalte des weichen Gaumens mit einseiti- ger Lippenspalte",
  "gruppen": [
   "SF",
   "SP3"
  ],
  "hinweis": ""
 },
 "Q37.4": {
  "diagnose": "Spalte des harten und des weichen Gau- mens mit beidseitiger Lippenspalte",
  "gruppen": [
   "SF",
   "SP3"
  ],
  "hinweis": ""
 },
 "Q37.5": {
  "diagnose": "Spalte des harten und des weichen Gau- mens mit einseitiger Lippenspalte",
  "gruppen": [
   "SF",
   "SP3"
  ],
  "hinweis": ""
 },
 "Q37.8": {
  "diagnose": "Gaumenspalte, nicht näher bezeichnet, mit beidseitiger Lippenspalte",
  "gruppen": [
   "SF",
   "SP3"
  ],
  "hinweis": ""
 },
 "Q37.9": {
  "diagnose": "Gaumenspalte, nicht näher bezeichnet, mit einseitiger Lippenspalte",
  "gruppen": [
   "SF",
   "SP3"
  ],
  "hinweis": ""
 },
 "F80.1": {
  "diagnose": "Expressive Sprachstörung",
  "gruppen": [
   "SP1",
   "SP2"
  ],
  "hinweis": "bis zum vollende- ten 12. Lebensjahr"
 },
 "F83": {
  "diagnose": "Kombinierte umschriebene Entwicklungs- störungen",
  "gruppen": [
   "EN1",
   "RE2",
   "SP1",
   "SP2",
   "SP3",
   "SP6",
   "ZN"
  ],
  "hinweis": "bis zum vollende- ten 18. Lebensjahr"
 },
 "F84.0": {
  "diagnose": "Frühkindlicher Autismus",
  "gruppen": [
   "EN1",
   "PS1",
   "SP1",
   "ZN"
  ],
  "hinweis": ""
 },
 "F84.1": {
  "diagnose": "Atypischer Autismus",
  "gruppen": [
   "EN1",
   "PS1",
   "SP1",
   "ZN"
  ],
  "hinweis": ""
 },
 "F84.3": {
  "diagnose": "Andere desintegrative Störung des Kin- desalters",
  "gruppen": [
   "EN1",
   "PS1",
   "SP1",
   "ZN"
  ],
  "hinweis": ""
 },
 "F84.4": {
  "diagnose": "Überaktive Störung mit Intelligenzminde- rung und Bewegungsstereotypien",
  "gruppen": [
   "EN1",
   "PS1",
   "SP1",
   "ZN"
  ],
  "hinweis": ""
 },
 "F84.5": {
  "diagnose": "Asperger-Syndrom",
  "gruppen": [
   "EN1",
   "PS1",
   "SP1",
   "ZN"
  ],
  "hinweis": ""
 },
 "F84.8": {
  "diagnose": "Sonstige tief greifende Entwicklungs- störungen",
  "gruppen": [
   "EN1",
   "PS1",
   "SP1",
   "ZN"
  ],
  "hinweis": ""
 },
 "F84.2": {
  "diagnose": "Rett-Syndrom",
  "gruppen": [
   "AT",
   "EN1",
   "EX",
   "PS1",
   "SB1",
   "SB3",
   "SC",
   "SP1",
   "WS",
   "ZN"
  ],
  "hinweis": ""
 },
 "Q90.0": {
  "diagnose": "Trisomie 21, meiotische Non-disjunction",
  "gruppen": [
   "EN1",
   "RE1",
   "SC",
   "SP1",
   "SP3",
   "ZN"
  ],
  "hinweis": ""
 },
 "Q90.1": {
  "diagnose": "Trisomie 21, Mosaik (mitotische Non-dis- junction)",
  "gruppen": [
   "EN1",
   "RE1",
   "SC",
   "SP1",
   "SP3",
   "ZN"
  ],
  "hinweis": ""
 },
 "Q90.2": {
  "diagnose": "Trisomie 21, Translokation",
  "gruppen": [
   "EN1",
   "RE1",
   "SC",
   "SP1",
   "SP3",
   "ZN"
  ],
  "hinweis": ""
 },
 "Q90.9": {
  "diagnose": "Down-Syndrom, nicht näher bezeichnet",
  "gruppen": [
   "EN1",
   "RE1",
   "SC",
   "SP1",
   "SP3",
   "ZN"
  ],
  "hinweis": ""
 },
 "Q91.0": {
  "diagnose": "Trisomie 18, meiotische Non-disjunction",
  "gruppen": [
   "EN1",
   "SP1",
   "ZN"
  ],
  "hinweis": ""
 },
 "Q91.1": {
  "diagnose": "Trisomie 18, Mosaik (mitotische Non-dis- junction)",
  "gruppen": [
   "EN1",
   "SP1",
   "ZN"
  ],
  "hinweis": ""
 },
 "Q91.2": {
  "diagnose": "Trisomie 18, Translokation",
  "gruppen": [
   "EN1",
   "SP1",
   "ZN"
  ],
  "hinweis": ""
 },
 "Q91.3": {
  "diagnose": "Edwards-Syndrom, nicht näher bezeich- net",
  "gruppen": [
   "EN1",
   "SP1",
   "ZN"
  ],
  "hinweis": ""
 },
 "Q91.4": {
  "diagnose": "Trisomie 13, meiotische Non-disjunction",
  "gruppen": [
   "EN1",
   "SP1",
   "ZN"
  ],
  "hinweis": ""
 },
 "Q91.5": {
  "diagnose": "Trisomie 13, Mosaik (mitotische Non-dis- junction)",
  "gruppen": [
   "EN1",
   "SP1",
   "ZN"
  ],
  "hinweis": ""
 },
 "Q91.6": {
  "diagnose": "Trisomie 13, Translokation",
  "gruppen": [
   "EN1",
   "SP1",
   "ZN"
  ],
  "hinweis": ""
 },
 "Q91.7": {
  "diagnose": "Patau-Syndrom, nicht näher bezeichnet",
  "gruppen": [
   "EN1",
   "SP1",
   "ZN"
  ],
  "hinweis": ""
 },
 "Q93.3": {
  "diagnose": "Deletion des kurzen Armes des Chromo- soms 4 (Wolf-Hirschhorn-Syndrom)",
  "gruppen": [
   "EX",
   "SB1",
   "SB2",
   "SP1",
   "WS"
  ],
  "hinweis": ""
 },
 "Q93.4": {
  "diagnose": "Deletion des kurzen Armes des Chromo- soms 5",
  "gruppen": [
   "EN1",
   "EX",
   "SP1",
   "WS",
   "ZN"
  ],
  "hinweis": ""
 },
 "Q93.5": {
  "diagnose": "Sonstige Deletion eines Chromosomen- teils (Angelmann-Syndrom)",
  "gruppen": [
   "EN1",
   "PS1",
   "SB1",
   "SB2",
   "SP1",
   "WS",
   "ZN"
  ],
  "hinweis": ""
 },
 "Q96.0": {
  "diagnose": "Karyotyp 45,X",
  "gruppen": [
   "EN1",
   "SP1",
   "ZN"
  ],
  "hinweis": ""
 },
 "Q96.1": {
  "diagnose": "Karyotyp 46,X iso (Xq)",
  "gruppen": [
   "EN1",
   "SP1",
   "ZN"
  ],
  "hinweis": ""
 },
 "Q96.2": {
  "diagnose": "Karyotyp 46,X mit Gonosomenanomalie, ausgenommen iso (Xq)",
  "gruppen": [
   "EN1",
   "SP1",
   "ZN"
  ],
  "hinweis": ""
 },
 "Q96.3": {
  "diagnose": "Mosaik, 45,X/46,XX oder 45,X/46,XY",
  "gruppen": [
   "EN1",
   "SP1",
   "ZN"
  ],
  "hinweis": ""
 },
 "Q96.4": {
  "diagnose": "Mosaik, 45,X/sonstige Zelllinie(n) mit Gonosomenanomalie",
  "gruppen": [
   "EN1",
   "SP1",
   "ZN"
  ],
  "hinweis": ""
 },
 "Q96.8": {
  "diagnose": "Sonstige Varianten des Turner-Syndroms",
  "gruppen": [
   "EN1",
   "SP1",
   "ZN"
  ],
  "hinweis": ""
 },
 "Q96.9": {
  "diagnose": "Turner-Syndrom, nicht näher bezeichnet",
  "gruppen": [
   "EN1",
   "SP1",
   "ZN"
  ],
  "hinweis": ""
 },
 "Q99.2": {
  "diagnose": "Fragiles X-Chromosom",
  "gruppen": [
   "EN1",
   "PS1",
   "PS2",
   "RE1",
   "RE2",
   "SB3",
   "SF",
   "SO2",
   "SP1",
   "SP3",
   "SP5",
   "ZN"
  ],
  "hinweis": ""
 },
 "J44.00": {
  "diagnose": "Chronische obstruktive Lungenkrankheit mit akuter Infektion der unteren Atemwe- ge: FEV₁ < 35% des Sollwertes",
  "gruppen": [
   "AT"
  ],
  "hinweis": ""
 },
 "J44.10": {
  "diagnose": "Chronische obstruktive Lungenkrankheit mit akuter Exazerbation, nicht näher be- zeichnet: FEV₁ < 35% des Sollwertes",
  "gruppen": [
   "AT"
  ],
  "hinweis": ""
 },
 "J44.80": {
  "diagnose": "Sonstige näher bezeichnete chronische obstruktive Lungenkrankheit: FEV₁ < 35% des Sollwertes",
  "gruppen": [
   "AT"
  ],
  "hinweis": ""
 },
 "J44.90": {
  "diagnose": "Chronische obstruktive Lungenkrankheit, nicht näher bezeichnet: FEV₁ < 35% des Sollwertes",
  "gruppen": [
   "AT"
  ],
  "hinweis": ""
 },
 "J84.10": {
  "diagnose": "Sonstige interstitielle Lungenkrankheiten mit Fibrose",
  "gruppen": [
   "AT"
  ],
  "hinweis": ""
 },
 "J84.80": {
  "diagnose": "Sonstige näher bezeichnete interstitielle Lungenkrankheiten",
  "gruppen": [
   "AT"
  ],
  "hinweis": ""
 },
 "P27.1": {
  "diagnose": "Bronchopulmonale Dysplasie mit Ursprung in der Perinatalperiode",
  "gruppen": [
   "AT"
  ],
  "hinweis": ""
 },
 "P27.8": {
  "diagnose": "Sonstige chronische Atemwegserkrankun- gen mit Ursprung in der Perinatalperiode",
  "gruppen": [
   "AT"
  ],
  "hinweis": ""
 },
 "E41": {
  "diagnose": "Alimentärer Marasmus",
  "gruppen": [
   "SC"
  ],
  "hinweis": "ab vollendetem 70. Lebensjahr, sofern dieser durch Schluckstörungen verursacht ist"
 },
 "F00.0": {
  "diagnose": "Demenz bei Alzheimer-Krankheit mit frühem Beginn (Typ 2)",
  "gruppen": [
   "PS4"
  ],
  "hinweis": ""
 },
 "F00.1": {
  "diagnose": "Demenz bei Alzheimer-Krankheit, mit spätem Beginn (Typ 1)",
  "gruppen": [
   "PS4"
  ],
  "hinweis": "ab vollendetem 70. Lebensjahr"
 },
 "F00.2": {
  "diagnose": "Demenz bei Alzheimer-Krankheit, atypi- sche oder gemischte Form",
  "gruppen": [
   "PS4"
  ],
  "hinweis": "ab vollendetem 70. Lebensjahr"
 },
 "F01.0": {
  "diagnose": "Vaskuläre Demenz mit akutem Beginn",
  "gruppen": [
   "PS4"
  ],
  "hinweis": "ab vollendetem 70. Lebensjahr"
 },
 "F01.1": {
  "diagnose": "Multiinfarkt-Demenz",
  "gruppen": [
   "PS4"
  ],
  "hinweis": "ab vollendetem 70. Lebensjahr"
 },
 "F01.2": {
  "diagnose": "Subkortikale vaskuläre Demenz",
  "gruppen": [
   "PS4"
  ],
  "hinweis": "ab vollendetem 70. Lebensjahr"
 },
 "F01.3": {
  "diagnose": "Gemischte kortikale und subkortikale vaskuläre Demenz",
  "gruppen": [
   "PS4"
  ],
  "hinweis": "ab vollendetem 70. Lebensjahr"
 },
 "F01.8": {
  "diagnose": "Sonstige vaskuläre Demenz",
  "gruppen": [
   "PS4"
  ],
  "hinweis": "ab vollendetem 70. Lebensjahr"
 },
 "F02.3": {
  "diagnose": "Demenz bei primärem Parkinson-Syn- drom",
  "gruppen": [
   "PS4"
  ],
  "hinweis": "ab vollendetem 70. Lebensjahr"
 },
 "F02.8": {
  "diagnose": "Demenz bei anderenorts klassifizierten Krankheitsbildern",
  "gruppen": [
   "PS4"
  ],
  "hinweis": "ab vollendetem 70. Lebensjahr"
 },
 "F03": {
  "diagnose": "Nicht näher bezeichnete Demenz",
  "gruppen": [
   "PS4"
  ],
  "hinweis": "ab vollendetem 70. Lebensjahr"
 },
 "F41.0": {
  "diagnose": "Panikstörung [episodisch paroxysmale Angst]",
  "gruppen": [
   "PS2"
  ],
  "hinweis": "ab vollendetem 70. Lebensjahr"
 },
 "F41.1": {
  "diagnose": "Generalisierte Angststörung",
  "gruppen": [
   "PS2"
  ],
  "hinweis": "ab vollendetem 70. Lebensjahr"
 },
 "F41.2": {
  "diagnose": "Angst und depressive Störung, gemischt",
  "gruppen": [
   "PS2"
  ],
  "hinweis": "ab vollendetem 70. Lebensjahr"
 },
 "F41.3": {
  "diagnose": "Andere gemischte Angststörungen",
  "gruppen": [
   "PS2"
  ],
  "hinweis": "ab vollendetem 70. Lebensjahr"
 },
 "F41.8": {
  "diagnose": "Sonstige spezifische Angststörungen",
  "gruppen": [
   "PS2"
  ],
  "hinweis": "ab vollendetem 70. Lebensjahr"
 },
 "F41.9": {
  "diagnose": "Angststörung, nicht näher bezeichnet",
  "gruppen": [
   "PS2"
  ],
  "hinweis": "ab vollendetem 70. Lebensjahr"
 },
 "F45.40": {
  "diagnose": "Anhaltende somatoforme Schmerzstörung",
  "gruppen": [
   "CS",
   "PS2"
  ],
  "hinweis": "ab vollendetem 70. Lebensjahr"
 },
 "F45.41": {
  "diagnose": "Chronische Schmerzstörung mit somati- schen und psychischen Faktoren",
  "gruppen": [
   "CS",
   "PS2"
  ],
  "hinweis": "ab vollendetem 70. Lebensjahr"
 },
 "G54.6": {
  "diagnose": "Phantomschmerz",
  "gruppen": [
   "CS",
   "PS2"
  ],
  "hinweis": "ab vollendetem 70. Lebensjahr"
 },
 "H82": {
  "diagnose": "Schwindelsyndrome bei anderenorts klassifizierten Krankheiten",
  "gruppen": [
   "EX",
   "SO3",
   "WS"
  ],
  "hinweis": "ab vollendetem 70. Lebensjahr"
 },
 "N39.3": {
  "diagnose": "Belastungsinkontinenz [Stressinkonti- nenz]",
  "gruppen": [
   "SO2"
  ],
  "hinweis": "ab vollendetem 70. Lebensjahr"
 },
 "R15": {
  "diagnose": "Stuhlinkontinenz",
  "gruppen": [
   "SO2"
  ],
  "hinweis": "ab vollendetem 70. Lebensjahr"
 },
 "R26.0": {
  "diagnose": "Ataktischer Gang",
  "gruppen": [
   "EX",
   "SO3",
   "WS"
  ],
  "hinweis": "ab vollendetem 70. Lebensjahr"
 },
 "R26.1": {
  "diagnose": "Paretischer Gang",
  "gruppen": [
   "EX",
   "SO3",
   "WS"
  ],
  "hinweis": "ab vollendetem 70. Lebensjahr"
 },
 "R26.2": {
  "diagnose": "Gehbeschwerden, anderenorts nicht klassifiziert",
  "gruppen": [
   "EX",
   "SO3",
   "WS"
  ],
  "hinweis": "ab vollendetem 70. Lebensjahr"
 },
 "R29.6": {
  "diagnose": "Sturzneigung, anderenorts nicht klassi- fiziert",
  "gruppen": [
   "EX",
   "SO3",
   "WS"
  ],
  "hinweis": "ab vollendetem 70. Lebensjahr"
 },
 "R32": {
  "diagnose": "Nicht näher bezeichnete Harninkontinenz",
  "gruppen": [
   "SO2"
  ],
  "hinweis": "ab vollendetem 70. Lebensjahr"
 },
 "R42": {
  "diagnose": "Schwindel und Taumel",
  "gruppen": [
   "EX",
   "SO3",
   "WS"
  ],
  "hinweis": "ab vollendetem 70. Lebensjahr"
 },
 "R52.1": {
  "diagnose": "Chronischer unbeeinflussbarer Schmerz",
  "gruppen": [
   "CS",
   "PS2"
  ],
  "hinweis": "ab vollendetem 70. Lebensjahr"
 },
 "R52.2": {
  "diagnose": "Sonstiger chronischer Schmerz",
  "gruppen": [
   "CS",
   "PS2"
  ],
  "hinweis": "ab vollendetem 70. Lebensjahr"
 },
 "R64": {
  "diagnose": "Kachexie",
  "gruppen": [
   "SC"
  ],
  "hinweis": "ab vollendetem 70. Lebensjahr"
 },
 "E74.0": {
  "diagnose": "Glykogenspeicherkrankheiten [Glyko- genose]",
  "gruppen": [
   "AT",
   "CS",
   "EN1",
   "EX",
   "PN",
   "SB1",
   "SB3",
   "SC",
   "SO1",
   "WS",
   "ZN"
  ],
  "hinweis": ""
 },
 "E75.0": {
  "diagnose": "GM2-Gangliosidose",
  "gruppen": [
   "AT",
   "CS",
   "EN1",
   "EX",
   "PN",
   "SB1",
   "SB3",
   "SC",
   "SO1",
   "WS",
   "ZN"
  ],
  "hinweis": ""
 },
 "E76.0": {
  "diagnose": "Mukopolysaccharidose, Typ I",
  "gruppen": [
   "AT",
   "CS",
   "EN1",
   "EX",
   "PN",
   "SB1",
   "SB3",
   "SC",
   "SO1",
   "WS",
   "ZN"
  ],
  "hinweis": ""
 },
 "E88.20": {
  "diagnose": "Lipödem, Stadium I",
  "gruppen": [
   "LY"
  ],
  "hinweis": "nur im Zusammen- hang mit komplexer physikalischer Entstauungs- therapie (Manuelle Lymphdrainage, Kompressions-the- rapie, Übungs-be- handlung/Be-we- gungstherapie und Hautpflege); es sind nicht immer alle Komponenten zeitgleich erforder- lich befristet bis 31.12.2027"
 },
 "E88.21": {
  "diagnose": "Lipödem, Stadium II",
  "gruppen": [
   "LY"
  ],
  "hinweis": "nur im Zusammen- hang mit komplexer physikalischer Entstauungs- therapie (Manuelle Lymphdrainage, Kompressions-the- rapie, Übungs-be- handlung/Be-we- gungstherapie und Hautpflege); es sind nicht immer alle Komponenten zeitgleich erforder- lich befristet bis 31.12.2027"
 },
 "E88.22": {
  "diagnose": "Lipödem, Stadium III",
  "gruppen": [
   "LY"
  ],
  "hinweis": "nur im Zusammen- hang mit komplexer physikalischer Entstauungs- therapie (Manuelle Lymphdrainage, Kompressions-the- rapie, Übungs-be- handlung/Be-we- gungstherapie und Hautpflege); es sind nicht immer alle Komponenten zeitgleich erforder- lich befristet bis 31.12.2027"
 },
 "U09.9": {
  "diagnose": "Post-COVID Syndrom",
  "gruppen": [
   "AT",
   "PS2",
   "PS3",
   "SB1",
   "WS"
  ],
  "hinweis": ""
 },
 "Z99.0": {
  "diagnose": "Abhängigkeit (langzeit) vom Aspirator i.V.m. Versorgung eines Tracheostomas",
  "gruppen": [
   "AT",
   "EN1",
   "EN2",
   "EN3",
   "EX",
   "LY",
   "PN",
   "SB1",
   "SB2",
   "SC",
   "ST1",
   "ZN"
  ],
  "hinweis": "Unter Einbindung der Ärztinnen und Ärzte, die die medizinische Behandlung der außerklinischen Intensivpflege ko- ordinieren"
 },
 "Z43.0": {
  "diagnose": "Abhängigkeit (langzeit) vom Aspirator i.V.m. Versorgung eines Tracheostomas",
  "gruppen": [
   "AT",
   "EN1",
   "EN2",
   "EN3",
   "EX",
   "LY",
   "PN",
   "SB1",
   "SB2",
   "SC",
   "ST1",
   "ZN"
  ],
  "hinweis": "Unter Einbindung der Ärztinnen und Ärzte, die die medizinische Behandlung der außerklinischen Intensivpflege ko- ordinieren"
 },
 "Z99.1": {
  "diagnose": "Abhängigkeit (langzeitig) vom Respirator",
  "gruppen": [
   "AT",
   "EN1",
   "EN2",
   "EN3",
   "EX",
   "LY",
   "PN",
   "SB1",
   "SB2",
   "SC",
   "ST1",
   "ZN"
  ],
  "hinweis": "Unter Einbindung der Ärztinnen und Ärzte, die die medizinische Behandlung der außerklinischen Intensivpflege ko- ordinieren"
 },
 "M13.11": {
  "diagnose": "EX",
  "gruppen": [],
  "hinweis": ""
 },
 "M13.81": {
  "diagnose": "EX",
  "gruppen": [],
  "hinweis": ""
 },
 "M13.91": {
  "diagnose": "EX",
  "gruppen": [],
  "hinweis": ""
 },
 "M19.01": {
  "diagnose": "EX",
  "gruppen": [],
  "hinweis": ""
 },
 "M19.11": {
  "diagnose": "EX",
  "gruppen": [],
  "hinweis": ""
 },
 "M19.21": {
  "diagnose": "EX",
  "gruppen": [],
  "hinweis": ""
 },
 "M19.81": {
  "diagnose": "EX",
  "gruppen": [],
  "hinweis": ""
 },
 "M19.91": {
  "diagnose": "EX",
  "gruppen": [],
  "hinweis": ""
 },
 "M24.11": {
  "diagnose": "EX",
  "gruppen": [],
  "hinweis": ""
 },
 "M24.21": {
  "diagnose": "EX",
  "gruppen": [],
  "hinweis": ""
 },
 "M24.31": {
  "diagnose": "EX",
  "gruppen": [],
  "hinweis": ""
 },
 "M24.51": {
  "diagnose": "EX",
  "gruppen": [],
  "hinweis": ""
 },
 "M24.61": {
  "diagnose": "EX",
  "gruppen": [],
  "hinweis": ""
 },
 "M24.81": {
  "diagnose": "EX",
  "gruppen": [],
  "hinweis": ""
 },
 "M24.91": {
  "diagnose": "EX",
  "gruppen": [],
  "hinweis": ""
 },
 "M25.01": {
  "diagnose": "EX",
  "gruppen": [],
  "hinweis": ""
 },
 "M25.11": {
  "diagnose": "EX",
  "gruppen": [],
  "hinweis": ""
 },
 "M25.21": {
  "diagnose": "EX",
  "gruppen": [],
  "hinweis": ""
 },
 "M25.31": {
  "diagnose": "EX",
  "gruppen": [],
  "hinweis": ""
 },
 "M25.41": {
  "diagnose": "EX",
  "gruppen": [],
  "hinweis": ""
 },
 "M25.61": {
  "diagnose": "EX",
  "gruppen": [],
  "hinweis": ""
 },
 "M65.01": {
  "diagnose": "EX",
  "gruppen": [],
  "hinweis": ""
 },
 "M65.11": {
  "diagnose": "EX",
  "gruppen": [],
  "hinweis": ""
 },
 "M65.81": {
  "diagnose": "EX",
  "gruppen": [],
  "hinweis": ""
 },
 "M65.91": {
  "diagnose": "EX",
  "gruppen": [],
  "hinweis": ""
 },
 "M66.11": {
  "diagnose": "EX",
  "gruppen": [],
  "hinweis": ""
 },
 "M66.21": {
  "diagnose": "EX",
  "gruppen": [],
  "hinweis": ""
 },
 "M66.31": {
  "diagnose": "EX",
  "gruppen": [],
  "hinweis": ""
 },
 "M66.41": {
  "diagnose": "EX",
  "gruppen": [],
  "hinweis": ""
 },
 "M71.01": {
  "diagnose": "EX",
  "gruppen": [],
  "hinweis": ""
 },
 "M71.11": {
  "diagnose": "EX",
  "gruppen": [],
  "hinweis": ""
 },
 "M71.31": {
  "diagnose": "EX",
  "gruppen": [],
  "hinweis": ""
 },
 "M71.81": {
  "diagnose": "EX",
  "gruppen": [],
  "hinweis": ""
 },
 "M71.91": {
  "diagnose": "EX",
  "gruppen": [],
  "hinweis": ""
 },
 "M84.11": {
  "diagnose": "EX",
  "gruppen": [],
  "hinweis": ""
 },
 "M84.81": {
  "diagnose": "EX",
  "gruppen": [],
  "hinweis": ""
 },
 "M84.91": {
  "diagnose": "EX",
  "gruppen": [],
  "hinweis": ""
 },
 "M93.21": {
  "diagnose": "EX",
  "gruppen": [],
  "hinweis": ""
 },
 "M93.81": {
  "diagnose": "EX",
  "gruppen": [],
  "hinweis": ""
 },
 "M94.21": {
  "diagnose": "EX",
  "gruppen": [],
  "hinweis": ""
 },
 "M94.31": {
  "diagnose": "EX",
  "gruppen": [],
  "hinweis": ""
 },
 "M94.81": {
  "diagnose": "EX",
  "gruppen": [],
  "hinweis": ""
 },
 "M94.91": {
  "diagnose": "EX",
  "gruppen": [],
  "hinweis": ""
 },
 "S42.3": {
  "diagnose": "EX",
  "gruppen": [],
  "hinweis": ""
 },
 "S42.7": {
  "diagnose": "EX",
  "gruppen": [],
  "hinweis": ""
 },
 "S42.8": {
  "diagnose": "EX",
  "gruppen": [],
  "hinweis": ""
 },
 "S42.9": {
  "diagnose": "EX",
  "gruppen": [],
  "hinweis": ""
 },
 "T22.30": {
  "diagnose": "EX",
  "gruppen": [],
  "hinweis": ""
 },
 "T22.32": {
  "diagnose": "EX",
  "gruppen": [],
  "hinweis": ""
 },
 "T22.33": {
  "diagnose": "EX",
  "gruppen": [],
  "hinweis": ""
 },
 "T84.00": {
  "diagnose": "EX",
  "gruppen": [],
  "hinweis": ""
 },
 "T84.10": {
  "diagnose": "EX",
  "gruppen": [],
  "hinweis": ""
 },
 "M84.01": {
  "diagnose": "EX",
  "gruppen": [],
  "hinweis": ""
 },
 "M84.21": {
  "diagnose": "EX",
  "gruppen": [],
  "hinweis": ""
 },
 "M84.31": {
  "diagnose": "EX",
  "gruppen": [],
  "hinweis": ""
 },
 "M84.41": {
  "diagnose": "EX",
  "gruppen": [],
  "hinweis": ""
 }
}